pip_upgrade_pkgs/__init__.py
pip_upgrade_pkgs/pip_upgrade_pkgs.py
pip_upgrade_pkgs/upgrade_pip_packages.py
pip_upgrade_pkgs-0.0.1.dist-info/METADATA
pip_upgrade_pkgs-0.0.1.dist-info/RECORD
pip_upgrade_pkgs-0.0.1.dist-info/WHEEL
pip_upgrade_pkgs-0.0.1.dist-info/entry_points.txt
pip_upgrade_pkgs-0.0.1.dist-info/top_level.txt
