Metadata-Version: 2.1
Name: pip-upgrade-pkgs
Version: 0.0.1
Summary: A single command to upgrade outdated "pip install --user" packages.
Home-page: https://github.com/sunbearc22/pip_upgrade_pkgs
Author: sunbearc22
Author-email: sunbear.c22@gmail.com
License: MIT
Keywords: pip upgrade packaging
Platform: UNKNOWN
Classifier: Development Status :: 3 - Alpha
Classifier: Intended Audience :: End Users/Desktop
Classifier: Intended Audience :: Developers
Classifier: Topic :: Software Development :: Build Tools
Classifier: Topic :: Software Development :: Libraries :: Python Modules
Classifier: Topic :: System :: Archiving :: Packaging
Classifier: Environment :: Console 
Classifier: License :: OSI Approved :: MIT License
Classifier: Operating System :: POSIX :: Linux
Classifier: Programming Language :: Python :: 3.5
Classifier: Programming Language :: Python :: 3.6
Classifier: Programming Language :: Python :: 3.7
Requires-Python: ~=3.5
Requires-Dist: pip (~=18.0)
